satdigitalinvoice/__init__.py
satdigitalinvoice/__version__.py
satdigitalinvoice/client_validation.py
satdigitalinvoice/email.py
satdigitalinvoice/environments.py
satdigitalinvoice/exceptions.py
satdigitalinvoice/facturacion.py
satdigitalinvoice/file_data_managers.py
satdigitalinvoice/gui_functions.py
satdigitalinvoice/initdb.py
satdigitalinvoice/layout.py
satdigitalinvoice/localdb.py
satdigitalinvoice/log_tools.py
satdigitalinvoice/mycfdi.py
satdigitalinvoice/prediales.py
satdigitalinvoice/sat_functions.py
satdigitalinvoice/setup_utils.py
satdigitalinvoice/utils.py
satdigitalinvoice/PySimpleGUI/PySimpleGUI.py
satdigitalinvoice/PySimpleGUI/__init__.py
satdigitalinvoice/formatting_functions/__init__.py
satdigitalinvoice/formatting_functions/common.py
satdigitalinvoice/images/logo.png
satdigitalinvoice/markdown_styles/markdown6.css
satdigitalinvoice/markdown_styles/markdown6_nopage.css
satdigitalinvoice/microsoft_auth/__init__.py
satdigitalinvoice/microsoft_auth/auth_code_receiver.py
satdigitalinvoice/microsoft_auth/cache_interactive_browser.py
satdigitalinvoice/microsoft_auth/cache_secret_client.py
satdigitalinvoice/microsoft_auth/get_keyvault_certificate.py
satdigitalinvoice/microsoft_auth/jwt_util.py
satdigitalinvoice/microsoft_auth/microsoft_oauth2.py
satdigitalinvoice/schemas/cliente.yaml
satdigitalinvoice/schemas/factura.yaml
satdigitalinvoice/schemas/producto.yaml
satdigitalinvoice-4.2.1.dist-info/METADATA
satdigitalinvoice-4.2.1.dist-info/WHEEL
satdigitalinvoice-4.2.1.dist-info/top_level.txt
satdigitalinvoice-4.2.1.dist-info/RECORD
