Metadata-Version: 2.4
Name: satdigitalinvoice
Version: 4.2.1
Summary: GUI APP to Generate CFDI
Home-page: https://github.com/SAT-CFDI/python-satdigitalinvoice
Author: CFDI Developer
Author-email: satcfdi@outlook.com
License: MIT License
Project-URL: Documentation, https://satdigitalinvoice.readthedocs.io
Project-URL: Source, https://github.com/SAT-CFDI/python-satdigitalinvoice
Keywords: cfdi,sat,facturación,comprobante,retenciones,nómina,pagos,carta porte,contabilidad,e-invoicing,DIOT
Classifier: Development Status :: 5 - Production/Stable
Classifier: Intended Audience :: Developers
Classifier: License :: OSI Approved :: MIT License
Classifier: Natural Language :: Spanish
Classifier: Operating System :: OS Independent
Classifier: Programming Language :: Python :: 3.11
Classifier: Programming Language :: Python :: 3.12
Requires-Python: >=3.11
Requires-Dist: satcfdi==4.8.2
Requires-Dist: diskcache
Requires-Dist: num2words
Requires-Dist: PyYAML
Requires-Dist: babel
Requires-Dist: markdown2
Requires-Dist: XlsxWriter
Requires-Dist: jsonschema
Requires-Dist: python-dateutil
Requires-Dist: babel
Requires-Dist: azure-identity
Requires-Dist: azure-keyvault
Provides-Extra: test
Requires-Dist: coverage; extra == "test"
Requires-Dist: pytest; extra == "test"
Dynamic: author
Dynamic: author-email
Dynamic: classifier
Dynamic: description
Dynamic: description-content-type
Dynamic: home-page
Dynamic: keywords
Dynamic: license
Dynamic: project-url
Dynamic: provides-extra
Dynamic: requires-dist
Dynamic: requires-python
Dynamic: summary
